src/__init__.py
src/server.py
hirebase_mcp-1.0.22.dist-info/METADATA
hirebase_mcp-1.0.22.dist-info/WHEEL
hirebase_mcp-1.0.22.dist-info/entry_points.txt
hirebase_mcp-1.0.22.dist-info/licenses/LICENSE
hirebase_mcp-1.0.22.dist-info/RECORD
