Metadata-Version: 2.4
Name: hirebase-mcp
Version: 1.0.22
Summary: HireBase MCP Server
Project-URL: Homepage, https://github.com/jhgaylor/hirebase-mcp
Project-URL: Repository, https://github.com/jhgaylor/hirebase-mcp
Project-URL: Bug Tracker, https://github.com/jhgaylor/hirebase-mcp/issues
Author-email: Jake Gaylor <jhgaylor@gmail.com>
License: MIT
License-File: LICENSE
Classifier: License :: OSI Approved :: MIT License
Classifier: Operating System :: OS Independent
Classifier: Programming Language :: Python :: 3
Classifier: Programming Language :: Python :: 3.10
Classifier: Programming Language :: Python :: 3.11
Classifier: Programming Language :: Python :: 3.12
Classifier: Topic :: Internet :: WWW/HTTP :: WSGI :: Application
Classifier: Topic :: Software Development :: Libraries :: Application Frameworks
Requires-Python: >=3.10
Requires-Dist: mcp[cli]
Requires-Dist: requests
Provides-Extra: dev
Requires-Dist: pyinstaller; extra == 'dev'
Provides-Extra: test
Requires-Dist: httpx; extra == 'test'
Requires-Dist: pytest-asyncio; extra == 'test'
Requires-Dist: pytest>=7.0; extra == 'test'
Requires-Dist: websockets; extra == 'test'
